busie_db/__init__.py
busie_db/db.py
busie_db/loaders.py
tests/__init__.py
tests/conftest.py
tests/test_db.py
tests/test_loaders.py
busie_db_helper-1.0.0.dist-info/LICENSE
busie_db_helper-1.0.0.dist-info/METADATA
busie_db_helper-1.0.0.dist-info/WHEEL
busie_db_helper-1.0.0.dist-info/top_level.txt
busie_db_helper-1.0.0.dist-info/RECORD
