Metadata-Version: 2.1
Name: busie-db-helper
Version: 1.0.0
Summary: A helper for flask sqlalchemy dbs
Home-page: UNKNOWN
Author: Brady Perry
Author-email: brady@getbusie.com
License: UNKNOWN
Platform: UNKNOWN
Classifier: Programming Language :: Python :: 3
Classifier: License :: OSI Approved :: MIT License
Classifier: Operating System :: OS Independent
Requires-Python: >=3.6
Requires-Dist: flask
Requires-Dist: flask-sqlalchemy
Requires-Dist: flask-migrate
Requires-Dist: sqlalchemy-utils
